taskkit/__init__.py
taskkit/backend.py
taskkit/event.py
taskkit/kit.py
taskkit/process.py
taskkit/py.typed
taskkit/result.py
taskkit/scheduler.py
taskkit/services.py
taskkit/signal.py
taskkit/stage.py
taskkit/task.py
taskkit/threads.py
taskkit/utils.py
taskkit/version.py
taskkit/worker.py
taskkit/contrib/__init__.py
taskkit/contrib/django/__init__.py
taskkit/contrib/django/apps.py
taskkit/contrib/django/models.py
taskkit/contrib/django/migrations/0001_initial.py
taskkit/contrib/django/migrations/0002_taskkittaskqueue.py
taskkit/contrib/django/migrations/0003_rename_taskkittask_done_began_taskkit_tas_done_e2b997_idx_and_more.py
taskkit/contrib/django/migrations/__init__.py
taskkit/impl/__init__.py
taskkit/impl/django.py
taskkit/impl/redis.py
taskkit-0.2.4.dist-info/licenses/LICENSE
taskkit-0.2.4.dist-info/METADATA
taskkit-0.2.4.dist-info/WHEEL
taskkit-0.2.4.dist-info/top_level.txt
taskkit-0.2.4.dist-info/RECORD
