Metadata-Version: 2.4
Name: taskkit
Version: 0.2.4
Summary: a distributed task runner
Home-page: https://github.com/saryou/taskkit
Author: Ryosuke Sasaki
Author-email: saryou.ssk@gmail.com
Project-URL: Bug Tracker, https://github.com/saryou/taskkit/issues
Classifier: Programming Language :: Python :: 3
Classifier: License :: OSI Approved :: MIT License
Classifier: Operating System :: OS Independent
Requires-Python: >=3.9
License-File: LICENSE
Requires-Dist: typing-extensions>=4.0.0
Dynamic: author
Dynamic: author-email
Dynamic: classifier
Dynamic: description
Dynamic: description-content-type
Dynamic: home-page
Dynamic: license-file
Dynamic: project-url
Dynamic: requires-dist
Dynamic: requires-python
Dynamic: summary
